diffonnx/__init__.py
diffonnx/base.py
diffonnx/cli.py
diffonnx/diff.py
diffonnx/runtime.py
diffonnx/static.py
diffonnx/structs.py
diffonnx/utils.py
diffonnx-1.0.2.dist-info/METADATA
diffonnx-1.0.2.dist-info/WHEEL
diffonnx-1.0.2.dist-info/entry_points.txt
diffonnx-1.0.2.dist-info/licenses/LICENSE
diffonnx-1.0.2.dist-info/RECORD
