Metadata-Version: 2.4
Name: diffonnx
Version: 1.0.2
Summary: Diff your ONNXs
Author-email: yuxuan-z <yuxuan-z19@qq.com>
License-File: LICENSE
Requires-Python: >=3.10
Requires-Dist: colorama>=0.4.6
Requires-Dist: grakel
Requires-Dist: numpy>=2.1.2
Requires-Dist: onnx>=1.18.0
Requires-Dist: onnxruntime>=1.22.1
Requires-Dist: onnxscript>=0.3.2
Requires-Dist: tabulate>=0.9.0
Provides-Extra: gpu
Requires-Dist: onnxruntime-gpu[cuda,cudnn]>=1.22.0; extra == 'gpu'
Provides-Extra: torch-cpu
Requires-Dist: torch>=2.5.0; extra == 'torch-cpu'
Provides-Extra: torch-cu124
Requires-Dist: onnxruntime-gpu[cuda,cudnn]>=1.22.0; extra == 'torch-cu124'
Requires-Dist: torch>=2.5.0; extra == 'torch-cu124'
